bansoko/__init__.py
bansoko/__main__.py
bansoko/game/__init__.py
bansoko/game/bundle.py
bansoko/game/context.py
bansoko/game/game_action.py
bansoko/game/game_object.py
bansoko/game/level.py
bansoko/game/level_template.py
bansoko/game/metadata_schema.py
bansoko/game/profile.py
bansoko/game/tiles.py
bansoko/game/screens/__init__.py
bansoko/game/screens/choose_level.py
bansoko/game/screens/error.py
bansoko/game/screens/exit.py
bansoko/game/screens/game_paused.py
bansoko/game/screens/gui_consts.py
bansoko/game/screens/how_to_play.py
bansoko/game/screens/level_completed.py
bansoko/game/screens/main_menu.py
bansoko/game/screens/playfield.py
bansoko/game/screens/screen_factory.py
bansoko/game/screens/victory.py
bansoko/gamedata/main.meta
bansoko/gamedata/main.pyxres
bansoko/graphics/__init__.py
bansoko/graphics/animation.py
bansoko/graphics/sprite.py
bansoko/graphics/text.py
bansoko/graphics/tilemap.py
bansoko/gui/__init__.py
bansoko/gui/input.py
bansoko/gui/menu.py
bansoko/gui/navigator.py
bansoko/gui/screen.py
bansoko-1.2.1.dist-info/LICENSE
bansoko-1.2.1.dist-info/METADATA
bansoko-1.2.1.dist-info/WHEEL
bansoko-1.2.1.dist-info/entry_points.txt
bansoko-1.2.1.dist-info/top_level.txt
bansoko-1.2.1.dist-info/RECORD
