Metadata-Version: 2.1
Name: bansoko
Version: 1.2.1
Summary: Bansoko is a reimagined, space-themed clone of MS-DOS Soko-Ban from 1984 created in Python using Pyxel
Home-page: https://github.com/kfurtak1024/bansoko
Author: Krzysztof Furtak
Author-email: contact@krzysztoffurtak.dev
Keywords: game puzzle sokoban 8-bit retro
Platform: any
Classifier: License :: OSI Approved :: MIT License
Classifier: Natural Language :: English
Classifier: Operating System :: OS Independent
Classifier: Programming Language :: Python :: 3.8
Classifier: Programming Language :: Python :: 3 :: Only
Classifier: Topic :: Games/Entertainment :: Puzzle Games
License-File: LICENSE
Requires-Dist: setuptools
Requires-Dist: pyxel
Requires-Dist: docopt
Requires-Dist: jsonschema
